{"verses":[{"id":4283,"verse_number":11,"verse_key":"42:11","hizb_number":49,"rub_el_hizb_number":193,"ruku_number":422,"manzil_number":6,"sajdah_number":null,"page_number":484,"juz_number":25,"words":[{"id":12204,"position":1,"audio_url":"wbw/042_011_001.mp3","char_type_name":"word","code_v1":"пӯ‘","code_v2":"пұҒ","page_number":484,"line_number":1,"text":"пұҒ","translation":{"text":"(The) Creator","language_name":"english"},"transliteration":{"text":"fДҒб№ӯiru","language_name":"english"}},{"id":12205,"position":2,"audio_url":"wbw/042_011_002.mp3","char_type_name":"word","code_v1":"пӯ’","code_v2":"пұӮ","page_number":484,"line_number":1,"text":"пұӮ","translation":{"text":"(of) the heavens","language_name":"english"},"transliteration":{"text":"l-samДҒwДҒti","language_name":"english"}},{"id":12206,"position":3,"audio_url":"wbw/042_011_003.mp3","char_type_name":"word","code_v1":"пӯ“пӯ”","code_v2":"пұғпұ„","page_number":484,"line_number":1,"text":"пұғпұ„","translation":{"text":"and the earth","language_name":"english"},"transliteration":{"text":"wal-arбёҚi","language_name":"english"}},{"id":12208,"position":4,"audio_url":"wbw/042_011_005.mp3","char_type_name":"word","code_v1":"пӯ•","code_v2":"пұ…","page_number":484,"line_number":1,"text":"пұ…","translation":{"text":"He made","language_name":"english"},"transliteration":{"text":"jaКҝala","language_name":"english"}},{"id":12209,"position":5,"audio_url":"wbw/042_011_006.mp3","char_type_name":"word","code_v1":"пӯ–","code_v2":"пұҶ","page_number":484,"line_number":1,"text":"пұҶ","translation":{"text":"for you","language_name":"english"},"transliteration":{"text":"lakum","language_name":"english"}},{"id":12210,"position":6,"audio_url":"wbw/042_011_007.mp3","char_type_name":"word","code_v1":"пӯ—","code_v2":"пұҮ","page_number":484,"line_number":1,"text":"пұҮ","translation":{"text":"from","language_name":"english"},"transliteration":{"text":"min","language_name":"english"}},{"id":12211,"position":7,"audio_url":"wbw/042_011_008.mp3","char_type_name":"word","code_v1":"пӯҳ","code_v2":"пұҲ","page_number":484,"line_number":1,"text":"пұҲ","translation":{"text":"yourselves","language_name":"english"},"transliteration":{"text":"anfusikum","language_name":"english"}},{"id":12212,"position":8,"audio_url":"wbw/042_011_009.mp3","char_type_name":"word","code_v1":"пӯҷ","code_v2":"пұү","page_number":484,"line_number":1,"text":"пұү","translation":{"text":"mates","language_name":"english"},"transliteration":{"text":"azwДҒjan","language_name":"english"}},{"id":12213,"position":9,"audio_url":"wbw/042_011_010.mp3","char_type_name":"word","code_v1":"пӯҡ","code_v2":"пұҠ","page_number":484,"line_number":2,"text":"пұҠ","translation":{"text":"and among","language_name":"english"},"transliteration":{"text":"wamina","language_name":"english"}},{"id":12214,"position":10,"audio_url":"wbw/042_011_011.mp3","char_type_name":"word","code_v1":"пӯӣ","code_v2":"пұӢ","page_number":484,"line_number":2,"text":"пұӢ","translation":{"text":"the cattle","language_name":"english"},"transliteration":{"text":"l-anКҝДҒmi","language_name":"english"}},{"id":12215,"position":11,"audio_url":"wbw/042_011_012.mp3","char_type_name":"word","code_v1":"пӯңпӯқ","code_v2":"пұҢ","page_number":484,"line_number":2,"text":"пұҢ","translation":{"text":"mates","language_name":"english"},"transliteration":{"text":"azwДҒjan","language_name":"english"}},{"id":12217,"position":12,"audio_url":"wbw/042_011_014.mp3","char_type_name":"word","code_v1":"пӯһ","code_v2":"пұҚ","page_number":484,"line_number":2,"text":"пұҚ","translation":{"text":"He multiplies you","language_name":"english"},"transliteration":{"text":"yadhra-ukum","language_name":"english"}},{"id":12218,"position":13,"audio_url":"wbw/042_011_015.mp3","char_type_name":"word","code_v1":"пӯҹпӯ ","code_v2":"пұҺпұҸ","page_number":484,"line_number":2,"text":"пұҺпұҸ","translation":{"text":"thereby","language_name":"english"},"transliteration":{"text":"fД«hi","language_name":"english"}},{"id":12220,"position":14,"audio_url":"wbw/042_011_017.mp3","char_type_name":"word","code_v1":"пӯЎ","code_v2":"пұҗ","page_number":484,"line_number":2,"text":"пұҗ","translation":{"text":"(There) is not","language_name":"english"},"transliteration":{"text":"laysa","language_name":"english"}},{"id":12221,"position":15,"audio_url":"wbw/042_011_018.mp3","char_type_name":"word","code_v1":"пӯў","code_v2":"пұ‘","page_number":484,"line_number":2,"text":"пұ‘","translation":{"text":"like Him","language_name":"english"},"transliteration":{"text":"kamith'lihi","language_name":"english"}},{"id":12222,"position":16,"audio_url":"wbw/042_011_019.mp3","char_type_name":"word","code_v1":"пӯЈпӯӨ","code_v2":"пұ’пұ“","page_number":484,"line_number":2,"text":"пұ’пұ“","translation":{"text":"anything","language_name":"english"},"transliteration":{"text":"shayon","language_name":"english"}},{"id":12224,"position":17,"audio_url":"wbw/042_011_021.mp3","char_type_name":"word","code_v1":"пӯҘ","code_v2":"пұ”","page_number":484,"line_number":2,"text":"пұ”","translation":{"text":"and He","language_name":"english"},"transliteration":{"text":"wahuwa","language_name":"english"}},{"id":12225,"position":18,"audio_url":"wbw/042_011_022.mp3","char_type_name":"word","code_v1":"пӯҰ","code_v2":"пұ•","page_number":484,"line_number":3,"text":"пұ•","translation":{"text":"(is) the All-Hearer","language_name":"english"},"transliteration":{"text":"l-samД«Кҝu","language_name":"english"}},{"id":12226,"position":19,"audio_url":"wbw/042_011_023.mp3","char_type_name":"word","code_v1":"пӯ§","code_v2":"пұ–","page_number":484,"line_number":3,"text":"пұ–","translation":{"text":"the All-Seer","language_name":"english"},"transliteration":{"text":"l-baб№ЈД«ru","language_name":"english"}},{"id":12227,"position":20,"audio_url":null,"char_type_name":"end","code_v1":"пӯЁ","code_v2":"пұ—","page_number":484,"line_number":3,"text":"пұ—","translation":{"text":"(11)","language_name":"english"},"transliteration":{"text":null,"language_name":"english"}}]},{"id":4284,"verse_number":12,"verse_key":"42:12","hizb_number":49,"rub_el_hizb_number":193,"ruku_number":422,"manzil_number":6,"sajdah_number":null,"page_number":484,"juz_number":25,"words":[{"id":13565,"position":1,"audio_url":"wbw/042_012_001.mp3","char_type_name":"word","code_v1":"пӯ©","code_v2":"пұҳ","page_number":484,"line_number":3,"text":"пұҳ","translation":{"text":"To Him (belongs)","language_name":"english"},"transliteration":{"text":"lahu","language_name":"english"}},{"id":13566,"position":2,"audio_url":"wbw/042_012_002.mp3","char_type_name":"word","code_v1":"пӯӘ","code_v2":"пұҷ","page_number":484,"line_number":3,"text":"пұҷ","translation":{"text":"(the) keys","language_name":"english"},"transliteration":{"text":"maqДҒlД«du","language_name":"english"}},{"id":13567,"position":3,"audio_url":"wbw/042_012_003.mp3","char_type_name":"word","code_v1":"пӯ«","code_v2":"пұҡ","page_number":484,"line_number":3,"text":"пұҡ","translation":{"text":"(of) the heavens","language_name":"english"},"transliteration":{"text":"l-samДҒwДҒti","language_name":"english"}},{"id":13568,"position":4,"audio_url":"wbw/042_012_004.mp3","char_type_name":"word","code_v1":"пӯ¬пӯӯ","code_v2":"пұӣпұң","page_number":484,"line_number":3,"text":"пұӣпұң","translation":{"text":"and the earth","language_name":"english"},"transliteration":{"text":"wal-arбёҚi","language_name":"english"}},{"id":13570,"position":5,"audio_url":"wbw/042_012_006.mp3","char_type_name":"word","code_v1":"пӯ®","code_v2":"пұқ","page_number":484,"line_number":3,"text":"пұқ","translation":{"text":"He extends","language_name":"english"},"transliteration":{"text":"yabsuб№ӯu","language_name":"english"}},{"id":13571,"position":6,"audio_url":"wbw/042_012_007.mp3","char_type_name":"word","code_v1":"пӯҜ","code_v2":"пұһ","page_number":484,"line_number":4,"text":"пұһ","translation":{"text":"the provision","language_name":"english"},"transliteration":{"text":"l-riz'qa","language_name":"english"}},{"id":13572,"position":7,"audio_url":"wbw/042_012_008.mp3","char_type_name":"word","code_v1":"пӯ°","code_v2":"пұҹ","page_number":484,"line_number":4,"text":"пұҹ","translation":{"text":"for whom","language_name":"english"},"transliteration":{"text":"liman","language_name":"english"}},{"id":13573,"position":8,"audio_url":"wbw/042_012_009.mp3","char_type_name":"word","code_v1":"пӯұ","code_v2":"пұ ","page_number":484,"line_number":4,"text":"пұ ","translation":{"text":"He wills","language_name":"english"},"transliteration":{"text":"yashДҒu","language_name":"english"}},{"id":13574,"position":9,"audio_url":"wbw/042_012_010.mp3","char_type_name":"word","code_v1":"пӯІпӯі","code_v2":"пұЎпұў","page_number":484,"line_number":4,"text":"пұЎпұў","translation":{"text":"and restricts","language_name":"english"},"transliteration":{"text":"wayaqdiru","language_name":"english"}},{"id":13576,"position":10,"audio_url":"wbw/042_012_012.mp3","char_type_name":"word","code_v1":"пӯҙ","code_v2":"пұЈ","page_number":484,"line_number":4,"text":"пұЈ","translation":{"text":"Indeed, He","language_name":"english"},"transliteration":{"text":"innahu","language_name":"english"}},{"id":13577,"position":11,"audio_url":"wbw/042_012_013.mp3","char_type_name":"word","code_v1":"пӯө","code_v2":"пұӨ","page_number":484,"line_number":4,"text":"пұӨ","translation":{"text":"of every","language_name":"english"},"transliteration":{"text":"bikulli","language_name":"english"}},{"id":13578,"position":12,"audio_url":"wbw/042_012_014.mp3","char_type_name":"word","code_v1":"пӯ¶","code_v2":"пұҘ","page_number":484,"line_number":4,"text":"пұҘ","translation":{"text":"thing","language_name":"english"},"transliteration":{"text":"shayin","language_name":"english"}},{"id":13579,"position":13,"audio_url":"wbw/042_012_015.mp3","char_type_name":"word","code_v1":"пӯ·","code_v2":"пұҰ","page_number":484,"line_number":4,"text":"пұҰ","translation":{"text":"(is) All-Knower","language_name":"english"},"transliteration":{"text":"КҝalД«mun","language_name":"english"}},{"id":13580,"position":14,"audio_url":null,"char_type_name":"end","code_v1":"пӯё","code_v2":"пұ§","page_number":484,"line_number":4,"text":"пұ§","translation":{"text":"(12)","language_name":"english"},"transliteration":{"text":null,"language_name":"english"}}]},{"id":4285,"verse_number":13,"verse_key":"42:13","hizb_number":49,"rub_el_hizb_number":194,"ruku_number":422,"manzil_number":6,"sajdah_number":null,"page_number":484,"juz_number":25,"words":[{"id":14726,"position":1,"audio_url":"wbw/042_013_002.mp3","char_type_name":"word","code_v1":"пӯ№ пӯә","code_v2":"пұЁ пұ©","page_number":484,"line_number":4,"text":"пұЁ пұ©","translation":{"text":"He has ordained","language_name":"english"},"transliteration":{"text":"sharaКҝa","language_name":"english"}},{"id":14727,"position":2,"audio_url":"wbw/042_013_003.mp3","char_type_name":"word","code_v1":"пӯ»","code_v2":"пұӘ","page_number":484,"line_number":5,"text":"пұӘ","translation":{"text":"for you","language_name":"english"},"transliteration":{"text":"lakum","language_name":"english"}},{"id":14728,"position":3,"audio_url":"wbw/042_013_004.mp3","char_type_name":"word","code_v1":"пӯј","code_v2":"пұ«","page_number":484,"line_number":5,"text":"пұ«","translation":{"text":"of","language_name":"english"},"transliteration":{"text":"mina","language_name":"english"}},{"id":14729,"position":4,"audio_url":"wbw/042_013_005.mp3","char_type_name":"word","code_v1":"пӯҪ","code_v2":"пұ¬","page_number":484,"line_number":5,"text":"пұ¬","translation":{"text":"the religion","language_name":"english"},"transliteration":{"text":"l-dД«ni","language_name":"english"}},{"id":14730,"position":5,"audio_url":"wbw/042_013_006.mp3","char_type_name":"word","code_v1":"пӯҫ","code_v2":"пұӯ","page_number":484,"line_number":5,"text":"пұӯ","translation":{"text":"what","language_name":"english"},"transliteration":{"text":"mДҒ","language_name":"english"}},{"id":14731,"position":6,"audio_url":"wbw/042_013_007.mp3","char_type_name":"word","code_v1":"пӯҝ","code_v2":"пұ®","page_number":484,"line_number":5,"text":"пұ®","translation":{"text":"He enjoined","language_name":"english"},"transliteration":{"text":"waб№Јб№ЈДҒ","language_name":"english"}},{"id":14732,"position":7,"audio_url":"wbw/042_013_008.mp3","char_type_name":"word","code_v1":"п®Җ","code_v2":"пұҜ","page_number":484,"line_number":5,"text":"пұҜ","translation":{"text":"upon","language_name":"english"},"transliteration":{"text":"bihi","language_name":"english"}},{"id":14733,"position":8,"audio_url":"wbw/042_013_009.mp3","char_type_name":"word","code_v1":"п®Ғ","code_v2":"пұ°","page_number":484,"line_number":5,"text":"пұ°","translation":{"text":"Nuh","language_name":"english"},"transliteration":{"text":"nЕ«бёҘan","language_name":"english"}},{"id":14734,"position":9,"audio_url":"wbw/042_013_010.mp3","char_type_name":"word","code_v1":"п®Ӯ","code_v2":"пұұ","page_number":484,"line_number":5,"text":"пұұ","translation":{"text":"and that which","language_name":"english"},"transliteration":{"text":"wa-alladhД«","language_name":"english"}},{"id":14735,"position":10,"audio_url":"wbw/042_013_011.mp3","char_type_name":"word","code_v1":"п®ғ","code_v2":"пұІ","page_number":484,"line_number":5,"text":"пұІ","translation":{"text":"We have revealed","language_name":"english"},"transliteration":{"text":"awбёҘaynДҒ","language_name":"english"}},{"id":14736,"position":11,"audio_url":"wbw/042_013_012.mp3","char_type_name":"word","code_v1":"п®„","code_v2":"пұі","page_number":484,"line_number":5,"text":"пұі","translation":{"text":"to you","language_name":"english"},"transliteration":{"text":"ilayka","language_name":"english"}},{"id":14737,"position":12,"audio_url":"wbw/042_013_013.mp3","char_type_name":"word","code_v1":"п®…","code_v2":"пұҙ","page_number":484,"line_number":5,"text":"пұҙ","translation":{"text":"and what","language_name":"english"},"transliteration":{"text":"wamДҒ","language_name":"english"}},{"id":14738,"position":13,"audio_url":"wbw/042_013_014.mp3","char_type_name":"word","code_v1":"п®Ҷ","code_v2":"пұө","page_number":484,"line_number":6,"text":"пұө","translation":{"text":"We enjoined","language_name":"english"},"transliteration":{"text":"waб№Јб№ЈaynДҒ","language_name":"english"}},{"id":14739,"position":14,"audio_url":"wbw/042_013_015.mp3","char_type_name":"word","code_v1":"п®Ү","code_v2":"пұ¶","page_number":484,"line_number":6,"text":"пұ¶","translation":{"text":"upon","language_name":"english"},"transliteration":{"text":"bihi","language_name":"english"}},{"id":14740,"position":15,"audio_url":"wbw/042_013_016.mp3","char_type_name":"word","code_v1":"п®Ҳ","code_v2":"пұ·","page_number":484,"line_number":6,"text":"пұ·","translation":{"text":"Ibrahim","language_name":"english"},"transliteration":{"text":"ib'rДҒhД«ma","language_name":"english"}},{"id":14741,"position":16,"audio_url":"wbw/042_013_017.mp3","char_type_name":"word","code_v1":"п®ү","code_v2":"пұё","page_number":484,"line_number":6,"text":"пұё","translation":{"text":"and Musa","language_name":"english"},"transliteration":{"text":"wamЕ«sДҒ","language_name":"english"}},{"id":14742,"position":17,"audio_url":"wbw/042_013_018.mp3","char_type_name":"word","code_v1":"п®Ҡп®Ӣ","code_v2":"пұ№пұә","page_number":484,"line_number":6,"text":"пұ№пұә","translation":{"text":"and Isa","language_name":"english"},"transliteration":{"text":"waКҝД«sДҒ","language_name":"english"}},{"id":14744,"position":18,"audio_url":"wbw/042_013_020.mp3","char_type_name":"word","code_v1":"п®Ң","code_v2":"пұ»","page_number":484,"line_number":6,"text":"пұ»","translation":{"text":"To","language_name":"english"},"transliteration":{"text":"an","language_name":"english"}},{"id":14745,"position":19,"audio_url":"wbw/042_013_021.mp3","char_type_name":"word","code_v1":"п®Қ","code_v2":"пұј","page_number":484,"line_number":6,"text":"пұј","translation":{"text":"establish","language_name":"english"},"transliteration":{"text":"aqД«mЕ«","language_name":"english"}},{"id":14746,"position":20,"audio_url":"wbw/042_013_022.mp3","char_type_name":"word","code_v1":"п®Һ","code_v2":"пұҪ","page_number":484,"line_number":6,"text":"пұҪ","translation":{"text":"the religion","language_name":"english"},"transliteration":{"text":"l-dД«na","language_name":"english"}},{"id":14747,"position":21,"audio_url":"wbw/042_013_023.mp3","char_type_name":"word","code_v1":"п®Ҹ","code_v2":"пұҫ","page_number":484,"line_number":7,"text":"пұҫ","translation":{"text":"and not","language_name":"english"},"transliteration":{"text":"walДҒ","language_name":"english"}},{"id":14748,"position":22,"audio_url":"wbw/042_013_024.mp3","char_type_name":"word","code_v1":"п®җ","code_v2":"пұҝ","page_number":484,"line_number":7,"text":"пұҝ","translation":{"text":"be divided","language_name":"english"},"transliteration":{"text":"tatafarraqЕ«","language_name":"english"}},{"id":14749,"position":23,"audio_url":"wbw/042_013_025.mp3","char_type_name":"word","code_v1":"п®‘п®’","code_v2":"пІҖпІҒ","page_number":484,"line_number":7,"text":"пІҖпІҒ","translation":{"text":"therein","language_name":"english"},"transliteration":{"text":"fД«hi","language_name":"english"}},{"id":14751,"position":24,"audio_url":"wbw/042_013_027.mp3","char_type_name":"word","code_v1":"п®“","code_v2":"пІӮ","page_number":484,"line_number":7,"text":"пІӮ","translation":{"text":"Is difficult","language_name":"english"},"transliteration":{"text":"kabura","language_name":"english"}},{"id":14752,"position":25,"audio_url":"wbw/042_013_028.mp3","char_type_name":"word","code_v1":"п®”","code_v2":"пІғ","page_number":484,"line_number":7,"text":"пІғ","translation":{"text":"on","language_name":"english"},"transliteration":{"text":"КҝalДҒ","language_name":"english"}},{"id":14753,"position":26,"audio_url":"wbw/042_013_029.mp3","char_type_name":"word","code_v1":"п®•","code_v2":"пІ„","page_number":484,"line_number":7,"text":"пІ„","translation":{"text":"the polytheists","language_name":"english"},"transliteration":{"text":"l-mush'rikД«na","language_name":"english"}},{"id":14754,"position":27,"audio_url":"wbw/042_013_030.mp3","char_type_name":"word","code_v1":"п®–","code_v2":"пІ…","page_number":484,"line_number":7,"text":"пІ…","translation":{"text":"what","language_name":"english"},"transliteration":{"text":"mДҒ","language_name":"english"}},{"id":14755,"position":28,"audio_url":"wbw/042_013_031.mp3","char_type_name":"word","code_v1":"п®—","code_v2":"пІҶ","page_number":484,"line_number":7,"text":"пІҶ","translation":{"text":"you call them","language_name":"english"},"transliteration":{"text":"tadКҝЕ«hum","language_name":"english"}},{"id":14756,"position":29,"audio_url":"wbw/042_013_032.mp3","char_type_name":"word","code_v1":"п®ҳп®ҷ","code_v2":"пІҮпІҲ","page_number":484,"line_number":7,"text":"пІҮпІҲ","translation":{"text":"to it","language_name":"english"},"transliteration":{"text":"ilayhi","language_name":"english"}},{"id":14758,"position":30,"audio_url":"wbw/042_013_034.mp3","char_type_name":"word","code_v1":"п®ҡ","code_v2":"пІү","page_number":484,"line_number":7,"text":"пІү","translation":{"text":"Allah","language_name":"english"},"transliteration":{"text":"l-lahu","language_name":"english"}},{"id":14759,"position":31,"audio_url":"wbw/042_013_035.mp3","char_type_name":"word","code_v1":"п®ӣ","code_v2":"пІҠ","page_number":484,"line_number":8,"text":"пІҠ","translation":{"text":"chooses","language_name":"english"},"transliteration":{"text":"yajtabД«","language_name":"english"}},{"id":14760,"position":32,"audio_url":"wbw/042_013_036.mp3","char_type_name":"word","code_v1":"п®ң","code_v2":"пІӢ","page_number":484,"line_number":8,"text":"пІӢ","translation":{"text":"for Himself","language_name":"english"},"transliteration":{"text":"ilayhi","language_name":"english"}},{"id":14761,"position":33,"audio_url":"wbw/042_013_037.mp3","char_type_name":"word","code_v1":"п®қ","code_v2":"пІҢ","page_number":484,"line_number":8,"text":"пІҢ","translation":{"text":"whom","language_name":"english"},"transliteration":{"text":"man","language_name":"english"}},{"id":14762,"position":34,"audio_url":"wbw/042_013_038.mp3","char_type_name":"word","code_v1":"п®һ","code_v2":"пІҚ","page_number":484,"line_number":8,"text":"пІҚ","translation":{"text":"He wills","language_name":"english"},"transliteration":{"text":"yashДҒu","language_name":"english"}},{"id":14763,"position":35,"audio_url":"wbw/042_013_039.mp3","char_type_name":"word","code_v1":"п®ҹ","code_v2":"пІҺ","page_number":484,"line_number":8,"text":"пІҺ","translation":{"text":"and guides","language_name":"english"},"transliteration":{"text":"wayahdД«","language_name":"english"}},{"id":14764,"position":36,"audio_url":"wbw/042_013_040.mp3","char_type_name":"word","code_v1":"п® ","code_v2":"пІҸ","page_number":484,"line_number":8,"text":"пІҸ","translation":{"text":"to Himself","language_name":"english"},"transliteration":{"text":"ilayhi","language_name":"english"}},{"id":14765,"position":37,"audio_url":"wbw/042_013_041.mp3","char_type_name":"word","code_v1":"п®Ў","code_v2":"пІҗ","page_number":484,"line_number":8,"text":"пІҗ","translation":{"text":"whoever","language_name":"english"},"transliteration":{"text":"man","language_name":"english"}},{"id":14766,"position":38,"audio_url":"wbw/042_013_042.mp3","char_type_name":"word","code_v1":"п®ў","code_v2":"пІ‘","page_number":484,"line_number":8,"text":"пІ‘","translation":{"text":"turns","language_name":"english"},"transliteration":{"text":"yunД«bu","language_name":"english"}},{"id":14767,"position":39,"audio_url":null,"char_type_name":"end","code_v1":"п®Ј","code_v2":"пІ’","page_number":484,"line_number":8,"text":"пІ’","translation":{"text":"(13)","language_name":"english"},"transliteration":{"text":null,"language_name":"english"}}]},{"id":4286,"verse_number":14,"verse_key":"42:14","hizb_number":49,"rub_el_hizb_number":194,"ruku_number":422,"manzil_number":6,"sajdah_number":null,"page_number":484,"juz_number":25,"words":[{"id":15808,"position":1,"audio_url":"wbw/042_014_001.mp3","char_type_name":"word","code_v1":"п®Ө","code_v2":"пІ“","page_number":484,"line_number":8,"text":"пІ“","translation":{"text":"And not","language_name":"english"},"transliteration":{"text":"wamДҒ","language_name":"english"}},{"id":15809,"position":2,"audio_url":"wbw/042_014_002.mp3","char_type_name":"word","code_v1":"п®Ҙ","code_v2":"пІ”","page_number":484,"line_number":8,"text":"пІ”","translation":{"text":"they became divided","language_name":"english"},"transliteration":{"text":"tafarraqЕ«","language_name":"english"}},{"id":15810,"position":3,"audio_url":"wbw/042_014_003.mp3","char_type_name":"word","code_v1":"п®Ұ","code_v2":"пІ•","page_number":484,"line_number":9,"text":"пІ•","translation":{"text":"until","language_name":"english"},"transliteration":{"text":"illДҒ","language_name":"english"}},{"id":15811,"position":4,"audio_url":"wbw/042_014_004.mp3","char_type_name":"word","code_v1":"п®§","code_v2":"пІ–","page_number":484,"line_number":9,"text":"пІ–","translation":{"text":"after","language_name":"english"},"transliteration":{"text":"min","language_name":"english"}},{"id":15812,"position":5,"audio_url":"wbw/042_014_005.mp3","char_type_name":"word","code_v1":"п®Ё","code_v2":"пІ—","page_number":484,"line_number":9,"text":"пІ—","translation":{"text":"after","language_name":"english"},"transliteration":{"text":"baКҝdi","language_name":"english"}},{"id":15813,"position":6,"audio_url":"wbw/042_014_006.mp3","char_type_name":"word","code_v1":"п®©","code_v2":"пІҳ","page_number":484,"line_number":9,"text":"пІҳ","translation":{"text":"[what]","language_name":"english"},"transliteration":{"text":"mДҒ","language_name":"english"}},{"id":15814,"position":7,"audio_url":"wbw/042_014_007.mp3","char_type_name":"word","code_v1":"п®Ә","code_v2":"пІҷ","page_number":484,"line_number":9,"text":"пІҷ","translation":{"text":"came to them","language_name":"english"},"transliteration":{"text":"jДҒahumu","language_name":"english"}},{"id":15815,"position":8,"audio_url":"wbw/042_014_008.mp3","char_type_name":"word","code_v1":"п®«","code_v2":"пІҡ","page_number":484,"line_number":9,"text":"пІҡ","translation":{"text":"the knowledge","language_name":"english"},"transliteration":{"text":"l-Кҝil'mu","language_name":"english"}},{"id":15816,"position":9,"audio_url":"wbw/042_014_009.mp3","char_type_name":"word","code_v1":"п®¬","code_v2":"пІӣ","page_number":484,"line_number":9,"text":"пІӣ","translation":{"text":"(out of) rivalry","language_name":"english"},"transliteration":{"text":"baghyan","language_name":"english"}},{"id":15817,"position":10,"audio_url":"wbw/042_014_010.mp3","char_type_name":"word","code_v1":"п®ӯп®®","code_v2":"пІңпІқ","page_number":484,"line_number":9,"text":"пІңпІқ","translation":{"text":"among them","language_name":"english"},"transliteration":{"text":"baynahum","language_name":"english"}},{"id":15819,"position":11,"audio_url":"wbw/042_014_012.mp3","char_type_name":"word","code_v1":"п®Ҝ","code_v2":"пІһ","page_number":484,"line_number":9,"text":"пІһ","translation":{"text":"And if not","language_name":"english"},"transliteration":{"text":"walawlДҒ","language_name":"english"}},{"id":15820,"position":12,"audio_url":"wbw/042_014_013.mp3","char_type_name":"word","code_v1":"п®°","code_v2":"пІҹ","page_number":484,"line_number":9,"text":"пІҹ","translation":{"text":"(for) a word","language_name":"english"},"transliteration":{"text":"kalimatun","language_name":"english"}},{"id":15821,"position":13,"audio_url":"wbw/042_014_014.mp3","char_type_name":"word","code_v1":"п®ұ","code_v2":"пІ ","page_number":484,"line_number":9,"text":"пІ ","translation":{"text":"(that) preceded","language_name":"english"},"transliteration":{"text":"sabaqat","language_name":"english"}},{"id":15822,"position":14,"audio_url":"wbw/042_014_015.mp3","char_type_name":"word","code_v1":"пҜ“","code_v2":"пІЎ","page_number":484,"line_number":10,"text":"пІЎ","translation":{"text":"from","language_name":"english"},"transliteration":{"text":"min","language_name":"english"}},{"id":15823,"position":15,"audio_url":"wbw/042_014_016.mp3","char_type_name":"word","code_v1":"пҜ”","code_v2":"пІў","page_number":484,"line_number":10,"text":"пІў","translation":{"text":"your Lord","language_name":"english"},"transliteration":{"text":"rabbika","language_name":"english"}},{"id":15824,"position":16,"audio_url":"wbw/042_014_017.mp3","char_type_name":"word","code_v1":"пҜ•","code_v2":"пІЈ","page_number":484,"line_number":10,"text":"пІЈ","translation":{"text":"for","language_name":"english"},"transliteration":{"text":"ilДҒ","language_name":"english"}},{"id":15825,"position":17,"audio_url":"wbw/042_014_018.mp3","char_type_name":"word","code_v1":"пҜ–","code_v2":"пІӨ","page_number":484,"line_number":10,"text":"пІӨ","translation":{"text":"a term","language_name":"english"},"transliteration":{"text":"ajalin","language_name":"english"}},{"id":15826,"position":18,"audio_url":"wbw/042_014_019.mp3","char_type_name":"word","code_v1":"пҜ—","code_v2":"пІҘ","page_number":484,"line_number":10,"text":"пІҘ","translation":{"text":"specified","language_name":"english"},"transliteration":{"text":"musamman","language_name":"english"}},{"id":15827,"position":19,"audio_url":"wbw/042_014_020.mp3","char_type_name":"word","code_v1":"пҜҳ","code_v2":"пІҰ","page_number":484,"line_number":10,"text":"пІҰ","translation":{"text":"surely, it (would have) been settled","language_name":"english"},"transliteration":{"text":"laquбёҚiya","language_name":"english"}},{"id":15828,"position":20,"audio_url":"wbw/042_014_021.mp3","char_type_name":"word","code_v1":"пҜҷпҜҡ","code_v2":"пІ§пІЁ","page_number":484,"line_number":10,"text":"пІ§пІЁ","translation":{"text":"between them","language_name":"english"},"transliteration":{"text":"baynahum","language_name":"english"}},{"id":15830,"position":21,"audio_url":"wbw/042_014_023.mp3","char_type_name":"word","code_v1":"пҜӣ","code_v2":"пІ©","page_number":484,"line_number":10,"text":"пІ©","translation":{"text":"And indeed","language_name":"english"},"transliteration":{"text":"wa-inna","language_name":"english"}},{"id":15831,"position":22,"audio_url":"wbw/042_014_024.mp3","char_type_name":"word","code_v1":"пҜң","code_v2":"пІӘ","page_number":484,"line_number":10,"text":"пІӘ","translation":{"text":"those who","language_name":"english"},"transliteration":{"text":"alladhД«na","language_name":"english"}},{"id":15832,"position":23,"audio_url":"wbw/042_014_025.mp3","char_type_name":"word","code_v1":"пҜқ","code_v2":"пІ«","page_number":484,"line_number":10,"text":"пІ«","translation":{"text":"were made to inherit","language_name":"english"},"transliteration":{"text":"Е«rithЕ«","language_name":"english"}},{"id":15833,"position":24,"audio_url":"wbw/042_014_026.mp3","char_type_name":"word","code_v1":"пҜһ","code_v2":"пІ¬","page_number":484,"line_number":11,"text":"пІ¬","translation":{"text":"the Book","language_name":"english"},"transliteration":{"text":"l-kitДҒba","language_name":"english"}},{"id":15834,"position":25,"audio_url":"wbw/042_014_027.mp3","char_type_name":"word","code_v1":"пҜҹ","code_v2":"пІӯ","page_number":484,"line_number":11,"text":"пІӯ","translation":{"text":"after them","language_name":"english"},"transliteration":{"text":"min","language_name":"english"}},{"id":15835,"position":26,"audio_url":"wbw/042_014_028.mp3","char_type_name":"word","code_v1":"пҜ ","code_v2":"пІ®","page_number":484,"line_number":11,"text":"пІ®","translation":{"text":"after them","language_name":"english"},"transliteration":{"text":"baКҝdihim","language_name":"english"}},{"id":15836,"position":27,"audio_url":"wbw/042_014_029.mp3","char_type_name":"word","code_v1":"пҜЎ","code_v2":"пІҜ","page_number":484,"line_number":11,"text":"пІҜ","translation":{"text":"(are) surely in","language_name":"english"},"transliteration":{"text":"lafД«","language_name":"english"}},{"id":15837,"position":28,"audio_url":"wbw/042_014_030.mp3","char_type_name":"word","code_v1":"пҜў","code_v2":"пІ°","page_number":484,"line_number":11,"text":"пІ°","translation":{"text":"doubt","language_name":"english"},"transliteration":{"text":"shakkin","language_name":"english"}},{"id":15838,"position":29,"audio_url":"wbw/042_014_031.mp3","char_type_name":"word","code_v1":"пҜЈ","code_v2":"пІұ","page_number":484,"line_number":11,"text":"пІұ","translation":{"text":"concerning it ","language_name":"english"},"transliteration":{"text":"min'hu","language_name":"english"}},{"id":15839,"position":30,"audio_url":"wbw/042_014_032.mp3","char_type_name":"word","code_v1":"пҜӨ","code_v2":"пІІ","page_number":484,"line_number":11,"text":"пІІ","translation":{"text":"disquieting","language_name":"english"},"transliteration":{"text":"murД«bin","language_name":"english"}},{"id":15840,"position":31,"audio_url":null,"char_type_name":"end","code_v1":"пҜҘ","code_v2":"пІі","page_number":484,"line_number":11,"text":"пІі","translation":{"text":"(14)","language_name":"english"},"transliteration":{"text":null,"language_name":"english"}}]},{"id":4287,"verse_number":15,"verse_key":"42:15","hizb_number":49,"rub_el_hizb_number":194,"ruku_number":422,"manzil_number":6,"sajdah_number":null,"page_number":484,"juz_number":25,"words":[{"id":16924,"position":1,"audio_url":"wbw/042_015_001.mp3","char_type_name":"word","code_v1":"пҜҰ","code_v2":"пІҙ","page_number":484,"line_number":11,"text":"пІҙ","translation":{"text":"So to that","language_name":"english"},"transliteration":{"text":"falidhДҒlika","language_name":"english"}},{"id":16925,"position":2,"audio_url":"wbw/042_015_002.mp3","char_type_name":"word","code_v1":"пҜ§пҜЁ","code_v2":"пІөпІ¶","page_number":484,"line_number":12,"text":"пІөпІ¶","translation":{"text":"then invite","language_name":"english"},"transliteration":{"text":"fa-ud'Кҝu","language_name":"english"}},{"id":16927,"position":3,"audio_url":"wbw/042_015_004.mp3","char_type_name":"word","code_v1":"пҜ©","code_v2":"пІ·","page_number":484,"line_number":12,"text":"пІ·","translation":{"text":"and stand firm","language_name":"english"},"transliteration":{"text":"wa-is'taqim","language_name":"english"}},{"id":16928,"position":4,"audio_url":"wbw/042_015_005.mp3","char_type_name":"word","code_v1":"пҜӘ","code_v2":"пІё","page_number":484,"line_number":12,"text":"пІё","translation":{"text":"as","language_name":"english"},"transliteration":{"text":"kamДҒ","language_name":"english"}},{"id":16929,"position":5,"audio_url":"wbw/042_015_006.mp3","char_type_name":"word","code_v1":"пҜ«пҜ¬","code_v2":"пІ№пІә","page_number":484,"line_number":12,"text":"пІ№пІә","translation":{"text":"you are commanded","language_name":"english"},"transliteration":{"text":"umir'ta","language_name":"english"}},{"id":16931,"position":6,"audio_url":"wbw/042_015_008.mp3","char_type_name":"word","code_v1":"пҜӯ","code_v2":"пІ»","page_number":484,"line_number":12,"text":"пІ»","translation":{"text":"and (do) not","language_name":"english"},"transliteration":{"text":"walДҒ","language_name":"english"}},{"id":16932,"position":7,"audio_url":"wbw/042_015_009.mp3","char_type_name":"word","code_v1":"пҜ®","code_v2":"пІј","page_number":484,"line_number":12,"text":"пІј","translation":{"text":"follow","language_name":"english"},"transliteration":{"text":"tattabiКҝ","language_name":"english"}},{"id":16933,"position":8,"audio_url":"wbw/042_015_010.mp3","char_type_name":"word","code_v1":"пҜҜпҜ°","code_v2":"пІҪпІҫ","page_number":484,"line_number":12,"text":"пІҪпІҫ","translation":{"text":"their desires","language_name":"english"},"transliteration":{"text":"ahwДҒahum","language_name":"english"}},{"id":16935,"position":9,"audio_url":"wbw/042_015_012.mp3","char_type_name":"word","code_v1":"пҜұ","code_v2":"пІҝ","page_number":484,"line_number":12,"text":"пІҝ","translation":{"text":"but say","language_name":"english"},"transliteration":{"text":"waqul","language_name":"english"}},{"id":16936,"position":10,"audio_url":"wbw/042_015_013.mp3","char_type_name":"word","code_v1":"пҜІ","code_v2":"піҖ","page_number":484,"line_number":13,"text":"піҖ","translation":{"text":"I believe","language_name":"english"},"transliteration":{"text":"ДҒmantu","language_name":"english"}},{"id":16937,"position":11,"audio_url":"wbw/042_015_014.mp3","char_type_name":"word","code_v1":"пҜі","code_v2":"піҒ","page_number":484,"line_number":13,"text":"піҒ","translation":{"text":"in what","language_name":"english"},"transliteration":{"text":"bimДҒ","language_name":"english"}},{"id":16938,"position":12,"audio_url":"wbw/042_015_015.mp3","char_type_name":"word","code_v1":"пҜҙ","code_v2":"піӮ","page_number":484,"line_number":13,"text":"піӮ","translation":{"text":"Allah has sent down","language_name":"english"},"transliteration":{"text":"anzala","language_name":"english"}},{"id":16939,"position":13,"audio_url":"wbw/042_015_016.mp3","char_type_name":"word","code_v1":"пҜө","code_v2":"піғ","page_number":484,"line_number":13,"text":"піғ","translation":{"text":"Allah has sent down","language_name":"english"},"transliteration":{"text":"l-lahu","language_name":"english"}},{"id":16940,"position":14,"audio_url":"wbw/042_015_017.mp3","char_type_name":"word","code_v1":"пҜ¶","code_v2":"пі„","page_number":484,"line_number":13,"text":"пі„","translation":{"text":"of","language_name":"english"},"transliteration":{"text":"min","language_name":"english"}},{"id":16941,"position":15,"audio_url":"wbw/042_015_018.mp3","char_type_name":"word","code_v1":"пҜ·пҜё","code_v2":"пі…піҶ","page_number":484,"line_number":13,"text":"пі…піҶ","translation":{"text":"(the) Book","language_name":"english"},"transliteration":{"text":"kitДҒbin","language_name":"english"}},{"id":16943,"position":16,"audio_url":"wbw/042_015_020.mp3","char_type_name":"word","code_v1":"пҜ№","code_v2":"піҮ","page_number":484,"line_number":13,"text":"піҮ","translation":{"text":"and I am commanded","language_name":"english"},"transliteration":{"text":"wa-umir'tu","language_name":"english"}},{"id":16944,"position":17,"audio_url":"wbw/042_015_021.mp3","char_type_name":"word","code_v1":"пҜә","code_v2":"піҲ","page_number":484,"line_number":13,"text":"піҲ","translation":{"text":"that I do justice","language_name":"english"},"transliteration":{"text":"li-aКҝdila","language_name":"english"}},{"id":16945,"position":18,"audio_url":"wbw/042_015_022.mp3","char_type_name":"word","code_v1":"пҜ»пҜј","code_v2":"піүпіҠ","page_number":484,"line_number":13,"text":"піүпіҠ","translation":{"text":"between you","language_name":"english"},"transliteration":{"text":"baynakumu","language_name":"english"}},{"id":16947,"position":19,"audio_url":"wbw/042_015_024.mp3","char_type_name":"word","code_v1":"пҜҪ","code_v2":"піӢ","page_number":484,"line_number":14,"text":"піӢ","translation":{"text":"Allah","language_name":"english"},"transliteration":{"text":"l-lahu","language_name":"english"}},{"id":16948,"position":20,"audio_url":"wbw/042_015_025.mp3","char_type_name":"word","code_v1":"пҜҫ","code_v2":"піҢ","page_number":484,"line_number":14,"text":"піҢ","translation":{"text":"(is) our Lord","language_name":"english"},"transliteration":{"text":"rabbunДҒ","language_name":"english"}},{"id":16949,"position":21,"audio_url":"wbw/042_015_026.mp3","char_type_name":"word","code_v1":"пҜҝп°Җ","code_v2":"піҚпіҺ","page_number":484,"line_number":14,"text":"піҚпіҺ","translation":{"text":"and your Lord","language_name":"english"},"transliteration":{"text":"warabbukum","language_name":"english"}},{"id":16951,"position":22,"audio_url":"wbw/042_015_028.mp3","char_type_name":"word","code_v1":"п°Ғ","code_v2":"піҸ","page_number":484,"line_number":14,"text":"піҸ","translation":{"text":"For us","language_name":"english"},"transliteration":{"text":"lanДҒ","language_name":"english"}},{"id":16952,"position":23,"audio_url":"wbw/042_015_029.mp3","char_type_name":"word","code_v1":"п°Ӯ","code_v2":"піҗ","page_number":484,"line_number":14,"text":"піҗ","translation":{"text":"our deeds","language_name":"english"},"transliteration":{"text":"aКҝmДҒlunДҒ","language_name":"english"}},{"id":16953,"position":24,"audio_url":"wbw/042_015_030.mp3","char_type_name":"word","code_v1":"п°ғ","code_v2":"пі‘","page_number":484,"line_number":14,"text":"пі‘","translation":{"text":"and for you","language_name":"english"},"transliteration":{"text":"walakum","language_name":"english"}},{"id":16954,"position":25,"audio_url":"wbw/042_015_031.mp3","char_type_name":"word","code_v1":"п°„п°…","code_v2":"пі’пі“","page_number":484,"line_number":14,"text":"пі’пі“","translation":{"text":"your deeds","language_name":"english"},"transliteration":{"text":"aКҝmДҒlukum","language_name":"english"}},{"id":16956,"position":26,"audio_url":"wbw/042_015_033.mp3","char_type_name":"word","code_v1":"п°Ҷ","code_v2":"пі”","page_number":484,"line_number":14,"text":"пі”","translation":{"text":"(There is) no","language_name":"english"},"transliteration":{"text":"lДҒ","language_name":"english"}},{"id":16957,"position":27,"audio_url":"wbw/042_015_034.mp3","char_type_name":"word","code_v1":"п°Ү","code_v2":"пі•","page_number":484,"line_number":14,"text":"пі•","translation":{"text":"argument","language_name":"english"},"transliteration":{"text":"бёҘujjata","language_name":"english"}},{"id":16958,"position":28,"audio_url":"wbw/042_015_035.mp3","char_type_name":"word","code_v1":"п°Ҳ","code_v2":"пі–","page_number":484,"line_number":15,"text":"пі–","translation":{"text":"between us","language_name":"english"},"transliteration":{"text":"baynanДҒ","language_name":"english"}},{"id":16959,"position":29,"audio_url":"wbw/042_015_036.mp3","char_type_name":"word","code_v1":"п°үп°Ҡ","code_v2":"пі—піҳ","page_number":484,"line_number":15,"text":"пі—піҳ","translation":{"text":"and between you","language_name":"english"},"transliteration":{"text":"wabaynakumu","language_name":"english"}},{"id":16961,"position":30,"audio_url":"wbw/042_015_038.mp3","char_type_name":"word","code_v1":"п°Ӣ","code_v2":"піҷ","page_number":484,"line_number":15,"text":"піҷ","translation":{"text":"Allah","language_name":"english"},"transliteration":{"text":"l-lahu","language_name":"english"}},{"id":16962,"position":31,"audio_url":"wbw/042_015_039.mp3","char_type_name":"word","code_v1":"п°Ң","code_v2":"піҡ","page_number":484,"line_number":15,"text":"піҡ","translation":{"text":"will assemble","language_name":"english"},"transliteration":{"text":"yajmaКҝu","language_name":"english"}},{"id":16963,"position":32,"audio_url":"wbw/042_015_040.mp3","char_type_name":"word","code_v1":"п°Қп°Һ","code_v2":"піӣпің","page_number":484,"line_number":15,"text":"піӣпің","translation":{"text":"[between] us","language_name":"english"},"transliteration":{"text":"baynanДҒ","language_name":"english"}},{"id":16965,"position":33,"audio_url":"wbw/042_015_042.mp3","char_type_name":"word","code_v1":"п°Ҹ","code_v2":"піқ","page_number":484,"line_number":15,"text":"піқ","translation":{"text":"and to Him","language_name":"english"},"transliteration":{"text":"wa-ilayhi","language_name":"english"}},{"id":16966,"position":34,"audio_url":"wbw/042_015_043.mp3","char_type_name":"word","code_v1":"п°җ","code_v2":"піһ","page_number":484,"line_number":15,"text":"піһ","translation":{"text":"(is) the final return","language_name":"english"},"transliteration":{"text":"l-maб№ЈД«ru","language_name":"english"}},{"id":16967,"position":35,"audio_url":null,"char_type_name":"end","code_v1":"п°‘","code_v2":"піҹ","page_number":484,"line_number":15,"text":"піҹ","translation":{"text":"(15)","language_name":"english"},"transliteration":{"text":null,"language_name":"english"}}]}]}